modelbrick/__init__.py
modelbrick/layers/__init__.py
modelbrick/layers/layers.py
modelbrick/models/__init__.py
modelbrick/models/models.py
modelbrick-0.0.4.dist-info/METADATA
modelbrick-0.0.4.dist-info/WHEEL
modelbrick-0.0.4.dist-info/top_level.txt
modelbrick-0.0.4.dist-info/RECORD
