Metadata-Version: 2.1
Name: modelbrick
Version: 0.0.4
Summary: ML model brick
Home-page: https://git.owdev.net/Jimmy/modelbrick.git
Author: Jimmy Su
Author-email: jim83531@gmail.com
License: UNKNOWN
Platform: UNKNOWN
Classifier: Programming Language :: Python :: 3
Classifier: License :: OSI Approved :: Apache Software License
Classifier: Operating System :: OS Independent
Requires-Python: >=3.8
Requires-Dist: tensorflow (>=2.4.0)
